{"chunk_definitions":[{"row":9,"row_count":1,"visible":true,"expansion_state":0,"options":{"engine":"r","label":"unnamed-chunk-120"},"document_id":"A61BB18E","chunk_id":"cafrp4ndn1k0h","chunk_label":"unnamed-chunk-1"},{"row":48,"row_count":1,"visible":true,"expansion_state":0,"options":{"engine":"r","label":"unnamed-chunk-125"},"document_id":"A61BB18E","chunk_id":"cl4amxa2s74vt","chunk_label":"unnamed-chunk-2"},{"row":58,"row_count":1,"visible":true,"expansion_state":0,"options":{"engine":"r","label":"unnamed-chunk-128"},"document_id":"A61BB18E","chunk_id":"cgzjyfitcxudb","chunk_label":"unnamed-chunk-3"},{"row":91,"row_count":1,"visible":true,"expansion_state":0,"options":{"engine":"r","label":"unnamed-chunk-27"},"document_id":"A61BB18E","chunk_id":"c0iyr31kdmddt","chunk_label":"unnamed-chunk-4"},{"row":104,"row_count":1,"visible":true,"expansion_state":0,"options":{"engine":"r","label":"unnamed-chunk-45"},"document_id":"A61BB18E","chunk_id":"cr4q8xx48k12m","chunk_label":"unnamed-chunk-5"},{"row":115,"row_count":1,"visible":true,"expansion_state":0,"options":{"engine":"r","label":"unnamed-chunk-94"},"document_id":"A61BB18E","chunk_id":"cgy9uc2i8yey9","chunk_label":"unnamed-chunk-6"},{"row":119,"row_count":1,"visible":true,"expansion_state":0,"options":{"engine":"r","label":"unnamed-chunk-95"},"document_id":"A61BB18E","chunk_id":"cmyj0jiegzdo0","chunk_label":"unnamed-chunk-7"},{"row":125,"row_count":1,"visible":true,"expansion_state":0,"options":{"engine":"r","label":"unnamed-chunk-96"},"document_id":"A61BB18E","chunk_id":"cwfeogg1ju24l","chunk_label":"unnamed-chunk-8"},{"row":287,"row_count":1,"visible":true,"expansion_state":0,"options":{"engine":"r","label":"unnamed-chunk-204"},"document_id":"A61BB18E","chunk_id":"c1t0jmjfshvn4","chunk_label":"unnamed-chunk-18"},{"row":306,"row_count":1,"visible":true,"expansion_state":0,"options":{"engine":"r","label":"unnamed-chunk-216"},"document_id":"A61BB18E","chunk_id":"c5057x503e6jl","chunk_label":"unnamed-chunk-20"}],"doc_write_time":1656196945,"chunk_rendered_width":543}